<?xml version="1.0" encoding="UTF-8"?>
<fpmd:sample xmlns:fpmd="http://www.quantum-simulation.org/ns/fpmd/fpmd-1.0"
 xmlns:xsi="http://www.w3.org/2001/XMLSchema-instance"
 xsi:schemaLocation="http://www.quantum-simulation.org/ns/fpmd/fpmd-1.0 sample.xsd">
<description> First atomset in PBE400 file s0015/md060.r  </description>
<atomset>
<unit_cell 
    a=" 23.46000000   0.00000000   0.00000000"
    b="  0.00000000  23.46000000   0.00000000"
    c="  0.00000000   0.00000000  23.46000000" />
<species name="oxygen" href="O_HSCV_PBE-1.0.xml"/>
<species name="hydrogen" href="D_HSCV_PBE-1.0.xml"/>
  <atom name="O1" species="oxygen">
    <position> 0.71762267 12.86618504 -19.81735832 </position>
    <velocity> 0.00012007 0.00011353 0.00001153 </velocity>
  </atom>
  <atom name="O2" species="oxygen">
    <position> 5.73337909 -16.42974435 -5.89674497 </position>
    <velocity> -0.00024616 0.00005037 -0.00018993 </velocity>
  </atom>
  <atom name="O3" species="oxygen">
    <position> 0.76184670 4.78845330 -8.65564969 </position>
    <velocity> -0.00005174 -0.00008984 -0.00011375 </velocity>
  </atom>
  <atom name="O4" species="oxygen">
    <position> 9.36701496 17.35623340 -0.09629020 </position>
    <velocity> -0.00009256 -0.00002440 0.00012747 </velocity>
  </atom>
  <atom name="O5" species="oxygen">
    <position> -7.13980473 6.71373523 -23.82640371 </position>
    <velocity> -0.00012407 0.00025854 0.00000014 </velocity>
  </atom>
  <atom name="O6" species="oxygen">
    <position> -11.92295666 7.23178894 1.98796143 </position>
    <velocity> 0.00051218 -0.00007865 0.00000784 </velocity>
  </atom>
  <atom name="O7" species="oxygen">
    <position> -3.36651906 -10.02614341 17.76738775 </position>
    <velocity> -0.00009757 0.00010700 0.00044183 </velocity>
  </atom>
  <atom name="O8" species="oxygen">
    <position> -9.83470007 14.58246981 -0.05956791 </position>
    <velocity> -0.00011270 0.00032563 -0.00016953 </velocity>
  </atom>
  <atom name="O9" species="oxygen">
    <position> 16.39520905 -13.72746115 8.31682344 </position>
    <velocity> -0.00033436 -0.00014575 0.00001572 </velocity>
  </atom>
  <atom name="O10" species="oxygen">
    <position> -19.51291176 7.12007921 -0.28628102 </position>
    <velocity> 0.00014944 -0.00007671 0.00000833 </velocity>
  </atom>
  <atom name="O11" species="oxygen">
    <position> -2.66682310 7.76077497 8.53797395 </position>
    <velocity> -0.00003072 -0.00024685 0.00027997 </velocity>
  </atom>
  <atom name="O12" species="oxygen">
    <position> -0.13540370 0.07710010 -10.62283086 </position>
    <velocity> -0.00002352 -0.00035180 0.00028689 </velocity>
  </atom>
  <atom name="O13" species="oxygen">
    <position> -5.93623548 14.10053828 10.83256592 </position>
    <velocity> -0.00037080 0.00044190 -0.00007488 </velocity>
  </atom>
  <atom name="O14" species="oxygen">
    <position> -27.48382402 -8.32871167 2.99277675 </position>
    <velocity> 0.00034358 0.00006247 -0.00001913 </velocity>
  </atom>
  <atom name="O15" species="oxygen">
    <position> 1.50037855 -2.46693362 -20.51699748 </position>
    <velocity> 0.00013211 0.00009550 -0.00025793 </velocity>
  </atom>
  <atom name="O16" species="oxygen">
    <position> 3.68764650 3.73418052 -13.22690741 </position>
    <velocity> -0.00005529 0.00011890 0.00003160 </velocity>
  </atom>
  <atom name="O17" species="oxygen">
    <position> 3.04852349 -6.92375457 -4.18184416 </position>
    <velocity> 0.00033346 -0.00028217 0.00007621 </velocity>
  </atom>
  <atom name="O18" species="oxygen">
    <position> -8.23421939 -8.91628155 15.43466136 </position>
    <velocity> 0.00034897 -0.00014014 -0.00005881 </velocity>
  </atom>
  <atom name="O19" species="oxygen">
    <position> -7.98406124 -0.38990269 -2.45609203 </position>
    <velocity> 0.00021920 0.00003253 0.00023439 </velocity>
  </atom>
  <atom name="O20" species="oxygen">
    <position> 7.33783260 -2.55335634 3.48284813 </position>
    <velocity> 0.00000022 -0.00014862 -0.00004440 </velocity>
  </atom>
  <atom name="O21" species="oxygen">
    <position> 11.88699568 7.57535274 7.10272141 </position>
    <velocity> 0.00024316 -0.00001256 0.00006317 </velocity>
  </atom>
  <atom name="O22" species="oxygen">
    <position> -6.47515536 -5.59672010 -15.82664868 </position>
    <velocity> -0.00031426 -0.00032283 -0.00055606 </velocity>
  </atom>
  <atom name="O23" species="oxygen">
    <position> 7.49747314 -10.25299584 -4.50799183 </position>
    <velocity> 0.00011013 0.00016903 0.00012493 </velocity>
  </atom>
  <atom name="O24" species="oxygen">
    <position> 0.08978586 -6.50831464 -0.18252612 </position>
    <velocity> -0.00010293 -0.00008793 0.00021288 </velocity>
  </atom>
  <atom name="O25" species="oxygen">
    <position> -29.86677706 -13.25272241 3.01289487 </position>
    <velocity> 0.00000556 0.00003052 -0.00008381 </velocity>
  </atom>
  <atom name="O26" species="oxygen">
    <position> -0.19282293 10.16180124 -8.50631214 </position>
    <velocity> -0.00000102 -0.00018277 0.00012463 </velocity>
  </atom>
  <atom name="O27" species="oxygen">
    <position> -6.05329608 -15.26539233 -8.85692794 </position>
    <velocity> -0.00016685 0.00008003 0.00025577 </velocity>
  </atom>
  <atom name="O28" species="oxygen">
    <position> 7.30016673 5.04193527 3.25942476 </position>
    <velocity> 0.00023089 0.00010114 0.00006661 </velocity>
  </atom>
  <atom name="O29" species="oxygen">
    <position> -9.23283551 6.40077943 -5.16346451 </position>
    <velocity> 0.00008112 0.00054108 -0.00002825 </velocity>
  </atom>
  <atom name="O30" species="oxygen">
    <position> -3.81732956 -22.89289771 -5.00765785 </position>
    <velocity> 0.00011095 -0.00009741 0.00031446 </velocity>
  </atom>
  <atom name="O31" species="oxygen">
    <position> -1.40515120 7.78058868 -20.34858317 </position>
    <velocity> 0.00007999 -0.00027950 -0.00023676 </velocity>
  </atom>
  <atom name="O32" species="oxygen">
    <position> 9.98118662 4.44753737 -6.88863577 </position>
    <velocity> -0.00026665 0.00004403 0.00021126 </velocity>
  </atom>
  <atom name="O33" species="oxygen">
    <position> -14.78056633 2.99975142 11.63018618 </position>
    <velocity> 0.00015091 -0.00005208 0.00002709 </velocity>
  </atom>
  <atom name="O34" species="oxygen">
    <position> 4.51592196 -0.39184466 14.81444054 </position>
    <velocity> 0.00025875 -0.00008423 0.00006530 </velocity>
  </atom>
  <atom name="O35" species="oxygen">
    <position> 2.38594804 -14.18855549 10.39399790 </position>
    <velocity> -0.00027337 0.00011131 0.00006342 </velocity>
  </atom>
  <atom name="O36" species="oxygen">
    <position> -10.73608903 2.89790159 8.28740104 </position>
    <velocity> 0.00013778 0.00028856 -0.00004343 </velocity>
  </atom>
  <atom name="O37" species="oxygen">
    <position> 20.09663460 18.67852882 -3.15258940 </position>
    <velocity> 0.00024620 0.00016900 0.00003953 </velocity>
  </atom>
  <atom name="O38" species="oxygen">
    <position> 5.27601574 -14.42673887 6.19618077 </position>
    <velocity> -0.00011386 0.00000522 -0.00013244 </velocity>
  </atom>
  <atom name="O39" species="oxygen">
    <position> 19.32083123 -1.66697956 33.40003130 </position>
    <velocity> -0.00054284 0.00022414 0.00015286 </velocity>
  </atom>
  <atom name="O40" species="oxygen">
    <position> -18.56580409 12.53209491 0.07644955 </position>
    <velocity> -0.00010866 -0.00019503 -0.00018120 </velocity>
  </atom>
  <atom name="O41" species="oxygen">
    <position> 10.72624511 -13.81718699 -11.96103608 </position>
    <velocity> 0.00009356 -0.00005127 0.00023414 </velocity>
  </atom>
  <atom name="O42" species="oxygen">
    <position> 15.75027513 0.52999561 -11.11233190 </position>
    <velocity> 0.00043596 -0.00023211 -0.00059844 </velocity>
  </atom>
  <atom name="O43" species="oxygen">
    <position> -12.99669357 0.25574114 -3.98925462 </position>
    <velocity> 0.00010443 0.00025086 0.00019661 </velocity>
  </atom>
  <atom name="O44" species="oxygen">
    <position> 3.95867500 2.30541518 -4.33044309 </position>
    <velocity> -0.00005859 -0.00005428 0.00021238 </velocity>
  </atom>
  <atom name="O45" species="oxygen">
    <position> -3.16286653 -0.88215966 4.21333642 </position>
    <velocity> 0.00005602 -0.00009545 0.00001907 </velocity>
  </atom>
  <atom name="O46" species="oxygen">
    <position> -0.23139650 -19.78663461 20.98565411 </position>
    <velocity> -0.00005589 0.00010107 0.00010685 </velocity>
  </atom>
  <atom name="O47" species="oxygen">
    <position> 9.72474369 18.97582575 -5.55716002 </position>
    <velocity> 0.00035136 0.00005685 -0.00028517 </velocity>
  </atom>
  <atom name="O48" species="oxygen">
    <position> -10.24521533 -12.21301844 18.57407813 </position>
    <velocity> -0.00006031 -0.00027095 0.00045347 </velocity>
  </atom>
  <atom name="O49" species="oxygen">
    <position> 14.35875332 -3.33657871 -7.54442339 </position>
    <velocity> -0.00026056 -0.00000035 -0.00016362 </velocity>
  </atom>
  <atom name="O50" species="oxygen">
    <position> -13.96847385 -11.00638346 -20.26176848 </position>
    <velocity> 0.00048939 -0.00003539 0.00000139 </velocity>
  </atom>
  <atom name="O51" species="oxygen">
    <position> 1.07091112 -8.04870395 8.20897717 </position>
    <velocity> 0.00025957 0.00011179 -0.00014290 </velocity>
  </atom>
  <atom name="O52" species="oxygen">
    <position> 19.99327921 3.41221962 1.80957691 </position>
    <velocity> 0.00005896 0.00003237 -0.00012434 </velocity>
  </atom>
  <atom name="O53" species="oxygen">
    <position> -17.77874747 17.84034953 7.09199377 </position>
    <velocity> -0.00014660 -0.00004850 0.00010808 </velocity>
  </atom>
  <atom name="O54" species="oxygen">
    <position> 2.70659519 2.71300572 -18.17567713 </position>
    <velocity> -0.00028150 -0.00000554 0.00001239 </velocity>
  </atom>
  <atom name="O55" species="oxygen">
    <position> -3.93302235 4.41219964 11.77860407 </position>
    <velocity> -0.00014423 0.00005671 0.00004234 </velocity>
  </atom>
  <atom name="O56" species="oxygen">
    <position> 6.19676855 10.87921281 14.10799491 </position>
    <velocity> -0.00008910 -0.00013950 -0.00018684 </velocity>
  </atom>
  <atom name="O57" species="oxygen">
    <position> 10.13111992 -9.32807134 -15.18312182 </position>
    <velocity> -0.00008981 -0.00045233 0.00029369 </velocity>
  </atom>
  <atom name="O58" species="oxygen">
    <position> -16.90925228 -6.51539158 -8.97668467 </position>
    <velocity> 0.00006919 -0.00005789 -0.00010388 </velocity>
  </atom>
  <atom name="O59" species="oxygen">
    <position> -11.30956944 -2.44104607 7.98609836 </position>
    <velocity> 0.00004822 -0.00009826 0.00019686 </velocity>
  </atom>
  <atom name="O60" species="oxygen">
    <position> 7.82881599 -2.33850779 -13.18897019 </position>
    <velocity> -0.00020061 -0.00019605 -0.00007709 </velocity>
  </atom>
  <atom name="O61" species="oxygen">
    <position> 1.36875958 17.82156470 14.41057063 </position>
    <velocity> -0.00013327 -0.00013926 0.00022810 </velocity>
  </atom>
  <atom name="O62" species="oxygen">
    <position> 6.62107299 24.31628807 -0.07474055 </position>
    <velocity> -0.00012843 -0.00007872 -0.00038456 </velocity>
  </atom>
  <atom name="O63" species="oxygen">
    <position> -1.08996551 -9.30041469 12.34705774 </position>
    <velocity> -0.00005400 0.00010273 -0.00021025 </velocity>
  </atom>
  <atom name="O64" species="oxygen">
    <position> 16.40557751 -3.97163833 0.73308080 </position>
    <velocity> -0.00067113 -0.00015837 0.00037467 </velocity>
  </atom>
  <atom name="H1" species="hydrogen">
    <position> 0.10980630 11.20351615 -20.00796516 </position>
    <velocity> -0.00019110 -0.00040962 -0.00013886 </velocity>
  </atom>
  <atom name="H2" species="hydrogen">
    <position> 2.18100788 12.93009227 -21.19659950 </position>
    <velocity> 0.00078695 0.00097589 0.00004932 </velocity>
  </atom>
  <atom name="H3" species="hydrogen">
    <position> 4.27781474 -17.64045169 -5.49066512 </position>
    <velocity> 0.00043644 -0.00050706 0.00021637 </velocity>
  </atom>
  <atom name="H4" species="hydrogen">
    <position> 7.30146093 -17.37501795 -6.17967101 </position>
    <velocity> -0.00062500 0.00009880 0.00027421 </velocity>
  </atom>
  <atom name="H5" species="hydrogen">
    <position> -0.90158551 5.21493591 -9.26662659 </position>
    <velocity> -0.00073446 -0.00005936 0.00032216 </velocity>
  </atom>
  <atom name="H6" species="hydrogen">
    <position> 1.42135105 6.52501936 -8.09191052 </position>
    <velocity> 0.00117377 0.00079773 -0.00000205 </velocity>
  </atom>
  <atom name="H7" species="hydrogen">
    <position> 11.21612033 17.20885642 -0.05634895 </position>
    <velocity> 0.00053087 -0.00015241 -0.00058055 </velocity>
  </atom>
  <atom name="H8" species="hydrogen">
    <position> 8.96312821 17.49765739 -1.82783154 </position>
    <velocity> -0.00070266 0.00029595 -0.00009823 </velocity>
  </atom>
  <atom name="H9" species="hydrogen">
    <position> -7.61000760 6.13611474 -25.51327154 </position>
    <velocity> -0.00129395 0.00049278 0.00029983 </velocity>
  </atom>
  <atom name="H10" species="hydrogen">
    <position> -6.44430814 5.13702707 -22.95084066 </position>
    <velocity> 0.00069475 -0.00013727 -0.00017239 </velocity>
  </atom>
  <atom name="H11" species="hydrogen">
    <position> -11.45683884 7.45080541 3.77407533 </position>
    <velocity> -0.00009528 -0.00027410 -0.00004863 </velocity>
  </atom>
  <atom name="H12" species="hydrogen">
    <position> -10.30096448 6.97894156 1.14460918 </position>
    <velocity> 0.00040827 0.00027520 -0.00052491 </velocity>
  </atom>
  <atom name="H13" species="hydrogen">
    <position> -3.99303088 -10.69548218 19.48292248 </position>
    <velocity> -0.00039572 0.00000580 -0.00095470 </velocity>
  </atom>
  <atom name="H14" species="hydrogen">
    <position> -5.06120630 -9.76808348 16.87668991 </position>
    <velocity> 0.00018432 0.00024715 -0.00137812 </velocity>
  </atom>
  <atom name="H15" species="hydrogen">
    <position> -10.19899889 13.53265446 -1.50711988 </position>
    <velocity> 0.00088867 -0.00012403 0.00091420 </velocity>
  </atom>
  <atom name="H16" species="hydrogen">
    <position> -10.71970903 13.78700549 1.36875721 </position>
    <velocity> 0.00035749 0.00035314 -0.00035135 </velocity>
  </atom>
  <atom name="H17" species="hydrogen">
    <position> 18.03626294 -14.88875150 8.23224006 </position>
    <velocity> -0.00016835 0.00008551 -0.00019510 </velocity>
  </atom>
  <atom name="H18" species="hydrogen">
    <position> 16.25198862 -13.32741638 6.50122043 </position>
    <velocity> -0.00037049 -0.00015580 0.00021251 </velocity>
  </atom>
  <atom name="H19" species="hydrogen">
    <position> -21.21732166 6.47926702 -0.57858985 </position>
    <velocity> -0.00086692 0.00071265 0.00036588 </velocity>
  </atom>
  <atom name="H20" species="hydrogen">
    <position> -18.66653400 7.41014756 -1.95305589 </position>
    <velocity> -0.00106434 -0.00060934 -0.00065733 </velocity>
  </atom>
  <atom name="H21" species="hydrogen">
    <position> -1.53733599 8.65842506 9.62001606 </position>
    <velocity> -0.00053978 0.00184964 0.00023044 </velocity>
  </atom>
  <atom name="H22" species="hydrogen">
    <position> -2.94799721 6.17882020 9.47697346 </position>
    <velocity> -0.00040272 0.00055953 0.00024479 </velocity>
  </atom>
  <atom name="H23" species="hydrogen">
    <position> -1.20566416 0.33109480 -9.19317713 </position>
    <velocity> -0.00043656 0.00040423 0.00001363 </velocity>
  </atom>
  <atom name="H24" species="hydrogen">
    <position> -1.39806392 -0.90572276 -11.68304277 </position>
    <velocity> 0.00018058 0.00002775 -0.00082841 </velocity>
  </atom>
  <atom name="H25" species="hydrogen">
    <position> -6.39943635 12.32647722 10.28114934 </position>
    <velocity> -0.00071917 0.00022919 0.00034081 </velocity>
  </atom>
  <atom name="H26" species="hydrogen">
    <position> -4.12680334 14.12393632 11.43179973 </position>
    <velocity> -0.00145301 0.00031428 0.00075216 </velocity>
  </atom>
  <atom name="H27" species="hydrogen">
    <position> -27.36513855 -6.93640753 1.81552308 </position>
    <velocity> 0.00010964 0.00123570 -0.00066284 </velocity>
  </atom>
  <atom name="H28" species="hydrogen">
    <position> -25.74760683 -9.05542719 2.96498302 </position>
    <velocity> 0.00001915 -0.00027798 0.00095228 </velocity>
  </atom>
  <atom name="H29" species="hydrogen">
    <position> 1.54240880 -3.67205481 -19.09750640 </position>
    <velocity> 0.00085144 0.00046216 -0.00114266 </velocity>
  </atom>
  <atom name="H30" species="hydrogen">
    <position> -0.47513056 -1.94149627 -20.36451899 </position>
    <velocity> -0.00006649 0.00049357 -0.00071465 </velocity>
  </atom>
  <atom name="H31" species="hydrogen">
    <position> 2.35268455 3.43599191 -12.01987142 </position>
    <velocity> 0.00025229 -0.00075854 -0.00099133 </velocity>
  </atom>
  <atom name="H32" species="hydrogen">
    <position> 2.99475402 3.47250684 -14.92488316 </position>
    <velocity> -0.00090264 -0.00009193 -0.00090927 </velocity>
  </atom>
  <atom name="H33" species="hydrogen">
    <position> 2.53840135 -6.00418955 -5.78988664 </position>
    <velocity> -0.00068333 0.00008285 0.00054537 </velocity>
  </atom>
  <atom name="H34" species="hydrogen">
    <position> 4.60142365 -7.90083049 -4.96543357 </position>
    <velocity> -0.00050510 0.00047898 0.00076995 </velocity>
  </atom>
  <atom name="H35" species="hydrogen">
    <position> -7.83762597 -8.86187863 13.54877834 </position>
    <velocity> -0.00051725 -0.00031490 -0.00041368 </velocity>
  </atom>
  <atom name="H36" species="hydrogen">
    <position> -8.54106272 -7.20212976 15.84823495 </position>
    <velocity> -0.00070407 -0.00059021 0.00103977 </velocity>
  </atom>
  <atom name="H37" species="hydrogen">
    <position> -6.35579576 -0.14683078 -3.25353339 </position>
    <velocity> -0.00069866 -0.00003731 0.00000443 </velocity>
  </atom>
  <atom name="H38" species="hydrogen">
    <position> -7.72293643 -1.61540352 -1.03725427 </position>
    <velocity> 0.00028779 0.00004131 0.00101034 </velocity>
  </atom>
  <atom name="H39" species="hydrogen">
    <position> 7.96833917 -3.50085637 2.10943345 </position>
    <velocity> -0.00008212 -0.00010721 0.00016028 </velocity>
  </atom>
  <atom name="H40" species="hydrogen">
    <position> 8.71085318 -2.08761748 4.52428422 </position>
    <velocity> 0.00026001 -0.00052972 0.00064658 </velocity>
  </atom>
  <atom name="H41" species="hydrogen">
    <position> 10.44464571 8.15085745 8.17983425 </position>
    <velocity> 0.00117844 -0.00047509 -0.00135462 </velocity>
  </atom>
  <atom name="H42" species="hydrogen">
    <position> 13.46152956 8.08610312 7.98005380 </position>
    <velocity> 0.00022184 -0.00011036 -0.00031315 </velocity>
  </atom>
  <atom name="H43" species="hydrogen">
    <position> -5.71673070 -5.99364394 -17.43812577 </position>
    <velocity> -0.00051742 0.00097346 -0.00050355 </velocity>
  </atom>
  <atom name="H44" species="hydrogen">
    <position> -6.63583119 -7.16639729 -14.76144179 </position>
    <velocity> 0.00084862 -0.00039591 -0.00044857 </velocity>
  </atom>
  <atom name="H45" species="hydrogen">
    <position> 7.02369831 -10.56995556 -2.73746215 </position>
    <velocity> -0.00073318 0.00032248 0.00025541 </velocity>
  </atom>
  <atom name="H46" species="hydrogen">
    <position> 6.18999563 -11.05112200 -5.63899144 </position>
    <velocity> -0.00018317 0.00023613 0.00021334 </velocity>
  </atom>
  <atom name="H47" species="hydrogen">
    <position> 0.78187785 -4.89110560 0.22668250 </position>
    <velocity> 0.00111829 0.00073562 -0.00005414 </velocity>
  </atom>
  <atom name="H48" species="hydrogen">
    <position> 1.30926737 -7.00672705 -1.54127013 </position>
    <velocity> -0.00009666 -0.00009630 -0.00021996 </velocity>
  </atom>
  <atom name="H49" species="hydrogen">
    <position> -29.93002021 -11.41011711 2.57851574 </position>
    <velocity> 0.00164409 0.00022718 -0.00008522 </velocity>
  </atom>
  <atom name="H50" species="hydrogen">
    <position> -30.25474044 -14.14027348 1.47141550 </position>
    <velocity> 0.00037789 0.00029423 0.00034196 </velocity>
  </atom>
  <atom name="H51" species="hydrogen">
    <position> -0.66242104 11.10275210 -7.04157402 </position>
    <velocity> -0.00024349 -0.00093929 -0.00014264 </velocity>
  </atom>
  <atom name="H52" species="hydrogen">
    <position> -0.02204217 11.34651518 -9.84895620 </position>
    <velocity> -0.00019970 -0.00035327 -0.00071290 </velocity>
  </atom>
  <atom name="H53" species="hydrogen">
    <position> -6.64185628 -15.95635096 -7.20721850 </position>
    <velocity> 0.00067026 0.00049063 -0.00043163 </velocity>
  </atom>
  <atom name="H54" species="hydrogen">
    <position> -4.58400632 -14.13604942 -8.65145523 </position>
    <velocity> 0.00034700 -0.00005743 0.00074100 </velocity>
  </atom>
  <atom name="H55" species="hydrogen">
    <position> 9.04621792 5.58208938 2.61252720 </position>
    <velocity> -0.00052886 0.00028421 -0.00083425 </velocity>
  </atom>
  <atom name="H56" species="hydrogen">
    <position> 6.28698151 6.02497614 1.94043966 </position>
    <velocity> 0.00017926 0.00026854 -0.00054129 </velocity>
  </atom>
  <atom name="H57" species="hydrogen">
    <position> -10.69341446 5.47209370 -5.78670591 </position>
    <velocity> -0.00017914 0.00088472 -0.00054192 </velocity>
  </atom>
  <atom name="H58" species="hydrogen">
    <position> -9.90543271 8.23769542 -5.02044041 </position>
    <velocity> 0.00018591 -0.00032417 -0.00059453 </velocity>
  </atom>
  <atom name="H59" species="hydrogen">
    <position> -2.43722589 -21.72094469 -3.97692690 </position>
    <velocity> -0.00107399 0.00021053 0.00053645 </velocity>
  </atom>
  <atom name="H60" species="hydrogen">
    <position> -3.05090365 -24.60407327 -4.97818021 </position>
    <velocity> -0.00075043 0.00025862 -0.00001128 </velocity>
  </atom>
  <atom name="H61" species="hydrogen">
    <position> -1.61458896 7.19547811 -18.54760164 </position>
    <velocity> 0.00043954 0.00046066 -0.00117657 </velocity>
  </atom>
  <atom name="H62" species="hydrogen">
    <position> -2.95792661 8.62518913 -20.80573681 </position>
    <velocity> -0.00045375 -0.00035559 0.00036904 </velocity>
  </atom>
  <atom name="H63" species="hydrogen">
    <position> 9.90310515 3.81504821 -8.69758785 </position>
    <velocity> 0.00031018 -0.00022880 -0.00029722 </velocity>
  </atom>
  <atom name="H64" species="hydrogen">
    <position> 10.34218062 2.80390553 -5.68107511 </position>
    <velocity> 0.00015322 -0.00012874 -0.00032988 </velocity>
  </atom>
  <atom name="H65" species="hydrogen">
    <position> -16.37527397 3.57957319 10.77869666 </position>
    <velocity> -0.00055691 0.00030334 -0.00014277 </velocity>
  </atom>
  <atom name="H66" species="hydrogen">
    <position> -14.85845416 1.21581774 11.13786333 </position>
    <velocity> 0.00019012 -0.00058536 -0.00069055 </velocity>
  </atom>
  <atom name="H67" species="hydrogen">
    <position> 3.00174699 -0.27711416 13.94545922 </position>
    <velocity> -0.00041062 -0.00038173 -0.00019041 </velocity>
  </atom>
  <atom name="H68" species="hydrogen">
    <position> 5.62163125 0.55946628 13.76986851 </position>
    <velocity> 0.00058726 -0.00003970 -0.00163599 </velocity>
  </atom>
  <atom name="H69" species="hydrogen">
    <position> 2.83630363 -15.99924040 10.45018659 </position>
    <velocity> 0.00055460 -0.00098668 0.00061653 </velocity>
  </atom>
  <atom name="H70" species="hydrogen">
    <position> 3.16750911 -13.78830359 8.70537179 </position>
    <velocity> 0.00087207 0.00001632 0.00012385 </velocity>
  </atom>
  <atom name="H71" species="hydrogen">
    <position> -10.90864929 4.73876633 7.74625679 </position>
    <velocity> 0.00023757 -0.00034098 0.00040478 </velocity>
  </atom>
  <atom name="H72" species="hydrogen">
    <position> -12.17889007 3.08656770 9.58198225 </position>
    <velocity> 0.00041808 0.00034732 -0.00013024 </velocity>
  </atom>
  <atom name="H73" species="hydrogen">
    <position> 19.56241407 17.89984386 -4.78730512 </position>
    <velocity> -0.00052667 -0.00048020 -0.00084171 </velocity>
  </atom>
  <atom name="H74" species="hydrogen">
    <position> 21.55839923 17.73589300 -2.30100265 </position>
    <velocity> -0.00018155 0.00046709 0.00022752 </velocity>
  </atom>
  <atom name="H75" species="hydrogen">
    <position> 4.76961693 -13.21251361 4.91132912 </position>
    <velocity> 0.00027463 0.00098887 -0.00105046 </velocity>
  </atom>
  <atom name="H76" species="hydrogen">
    <position> 5.99779861 -16.02057355 5.47102128 </position>
    <velocity> -0.00028671 0.00057049 -0.00123590 </velocity>
  </atom>
  <atom name="H77" species="hydrogen">
    <position> 18.73527846 -3.42828796 32.58509303 </position>
    <velocity> -0.00011594 -0.00014865 -0.00050185 </velocity>
  </atom>
  <atom name="H78" species="hydrogen">
    <position> 19.84469167 -0.82850791 31.91165283 </position>
    <velocity> -0.00045150 -0.00011069 0.00122045 </velocity>
  </atom>
  <atom name="H79" species="hydrogen">
    <position> -16.93021945 12.84107505 1.00409026 </position>
    <velocity> -0.00051984 -0.00010449 -0.00053696 </velocity>
  </atom>
  <atom name="H80" species="hydrogen">
    <position> -18.66644258 10.77877822 -0.24929130 </position>
    <velocity> 0.00048045 0.00006311 0.00036694 </velocity>
  </atom>
  <atom name="H81" species="hydrogen">
    <position> 9.46447727 -13.30052937 -10.73221624 </position>
    <velocity> -0.00023284 -0.00039448 0.00032750 </velocity>
  </atom>
  <atom name="H82" species="hydrogen">
    <position> 12.31958030 -13.23144416 -11.07368554 </position>
    <velocity> -0.00003675 0.00034939 0.00031436 </velocity>
  </atom>
  <atom name="H83" species="hydrogen">
    <position> 16.72585824 -0.43222777 -12.35011233 </position>
    <velocity> 0.00037956 -0.00074993 -0.00077576 </velocity>
  </atom>
  <atom name="H84" species="hydrogen">
    <position> 14.60105060 1.27376504 -12.39031489 </position>
    <velocity> -0.00053711 -0.00120903 -0.00075987 </velocity>
  </atom>
  <atom name="H85" species="hydrogen">
    <position> -14.28986559 0.31815980 -2.66160085 </position>
    <velocity> 0.00028760 0.00066891 0.00054927 </velocity>
  </atom>
  <atom name="H86" species="hydrogen">
    <position> -11.38957532 -0.24071536 -3.29657562 </position>
    <velocity> -0.00000612 -0.00065746 0.00009334 </velocity>
  </atom>
  <atom name="H87" species="hydrogen">
    <position> 4.06201131 1.39214941 -5.98083656 </position>
    <velocity> -0.00003433 0.00050925 0.00072820 </velocity>
  </atom>
  <atom name="H88" species="hydrogen">
    <position> 5.00392810 1.42996039 -2.83219237 </position>
    <velocity> -0.00056696 -0.00044989 -0.00056316 </velocity>
  </atom>
  <atom name="H89" species="hydrogen">
    <position> -3.92612011 0.63656038 3.33240376 </position>
    <velocity> 0.00019513 0.00045462 -0.00012481 </velocity>
  </atom>
  <atom name="H90" species="hydrogen">
    <position> -4.31431056 -2.30176781 3.92210371 </position>
    <velocity> 0.00049718 -0.00073999 -0.00020639 </velocity>
  </atom>
  <atom name="H91" species="hydrogen">
    <position> -1.05225650 -18.86619352 19.54159100 </position>
    <velocity> 0.00031833 0.00046408 -0.00011956 </velocity>
  </atom>
  <atom name="H92" species="hydrogen">
    <position> 1.42516802 -20.41626324 20.10200578 </position>
    <velocity> 0.00118606 -0.00029969 -0.00075455 </velocity>
  </atom>
  <atom name="H93" species="hydrogen">
    <position> 9.58826803 20.78883128 -5.23471390 </position>
    <velocity> 0.00087143 -0.00046445 0.00093269 </velocity>
  </atom>
  <atom name="H94" species="hydrogen">
    <position> 11.13449117 18.98833170 -6.73830800 </position>
    <velocity> 0.00026858 -0.00020628 0.00110693 </velocity>
  </atom>
  <atom name="H95" species="hydrogen">
    <position> -12.09329414 -11.58947680 18.75526085 </position>
    <velocity> -0.00150178 0.00000485 0.00045520 </velocity>
  </atom>
  <atom name="H96" species="hydrogen">
    <position> -9.35242980 -11.19974814 17.32400512 </position>
    <velocity> -0.00033531 -0.00041112 0.00038477 </velocity>
  </atom>
  <atom name="H97" species="hydrogen">
    <position> 14.58466752 -1.96091787 -8.81915990 </position>
    <velocity> -0.00026864 0.00061355 0.00029299 </velocity>
  </atom>
  <atom name="H98" species="hydrogen">
    <position> 15.11297009 -2.72377961 -5.90214720 </position>
    <velocity> 0.00119006 0.00093503 -0.00009834 </velocity>
  </atom>
  <atom name="H99" species="hydrogen">
    <position> -13.83883924 -10.24921597 -18.52664532 </position>
    <velocity> 0.00042165 0.00068808 0.00048965 </velocity>
  </atom>
  <atom name="H100" species="hydrogen">
    <position> -13.37154626 -12.66874320 -20.22398856 </position>
    <velocity> -0.00040592 0.00027489 -0.00041089 </velocity>
  </atom>
  <atom name="H101" species="hydrogen">
    <position> 2.63350846 -7.18847214 7.75026609 </position>
    <velocity> 0.00046083 0.00014691 -0.00005865 </velocity>
  </atom>
  <atom name="H102" species="hydrogen">
    <position> 0.54959141 -9.18647747 6.69071200 </position>
    <velocity> 0.00000979 0.00017665 0.00032374 </velocity>
  </atom>
  <atom name="H103" species="hydrogen">
    <position> 20.88791309 4.94716869 2.58729247 </position>
    <velocity> 0.00154834 0.00000434 -0.00038386 </velocity>
  </atom>
  <atom name="H104" species="hydrogen">
    <position> 21.17584651 3.00655248 0.40479264 </position>
    <velocity> -0.00034199 0.00048912 0.00064137 </velocity>
  </atom>
  <atom name="H105" species="hydrogen">
    <position> -17.26228757 18.70962925 5.53617594 </position>
    <velocity> -0.00049317 -0.00028280 0.00103048 </velocity>
  </atom>
  <atom name="H106" species="hydrogen">
    <position> -17.40832239 19.06535821 8.43871216 </position>
    <velocity> -0.00095752 0.00034478 -0.00005567 </velocity>
  </atom>
  <atom name="H107" species="hydrogen">
    <position> 2.23092768 1.12884005 -18.92814408 </position>
    <velocity> -0.00005417 -0.00025281 -0.00025396 </velocity>
  </atom>
  <atom name="H108" species="hydrogen">
    <position> 4.49368792 2.73815754 -18.82296041 </position>
    <velocity> 0.00076749 0.00009377 -0.00048681 </velocity>
  </atom>
  <atom name="H109" species="hydrogen">
    <position> -5.06960941 3.06973433 11.23547496 </position>
    <velocity> -0.00039181 0.00024047 -0.00021505 </velocity>
  </atom>
  <atom name="H110" species="hydrogen">
    <position> -5.12936291 5.68585696 12.50316710 </position>
    <velocity> 0.00034567 -0.00009828 0.00020625 </velocity>
  </atom>
  <atom name="H111" species="hydrogen">
    <position> 4.58965944 10.53045166 13.17561529 </position>
    <velocity> 0.00040029 -0.00086324 0.00082005 </velocity>
  </atom>
  <atom name="H112" species="hydrogen">
    <position> 6.23499358 9.83581371 15.64645591 </position>
    <velocity> 0.00015416 -0.00023635 0.00070523 </velocity>
  </atom>
  <atom name="H113" species="hydrogen">
    <position> 10.05785890 -10.60949056 -13.87744870 </position>
    <velocity> -0.00026076 0.00104232 0.00016990 </velocity>
  </atom>
  <atom name="H114" species="hydrogen">
    <position> 8.46740184 -8.49993048 -15.31760752 </position>
    <velocity> 0.00044376 -0.00038050 -0.00014894 </velocity>
  </atom>
  <atom name="H115" species="hydrogen">
    <position> -16.47018276 -8.34969199 -9.37378349 </position>
    <velocity> 0.00082903 -0.00038403 0.00002520 </velocity>
  </atom>
  <atom name="H116" species="hydrogen">
    <position> -15.89737112 -5.99288677 -7.37905822 </position>
    <velocity> -0.00000866 -0.00001994 0.00041583 </velocity>
  </atom>
  <atom name="H117" species="hydrogen">
    <position> -9.68215954 -3.55087202 7.90499305 </position>
    <velocity> -0.00115652 -0.00033434 0.00024589 </velocity>
  </atom>
  <atom name="H118" species="hydrogen">
    <position> -10.96405181 -0.64533961 7.60199882 </position>
    <velocity> 0.00005104 0.00032819 -0.00077879 </velocity>
  </atom>
  <atom name="H119" species="hydrogen">
    <position> 9.54489990 -2.93166876 -13.82966847 </position>
    <velocity> 0.00040323 -0.00021082 -0.00013913 </velocity>
  </atom>
  <atom name="H120" species="hydrogen">
    <position> 7.70356342 -3.29517698 -11.61245210 </position>
    <velocity> 0.00021722 0.00074299 -0.00017866 </velocity>
  </atom>
  <atom name="H121" species="hydrogen">
    <position> 3.26717516 17.87584534 14.10605791 </position>
    <velocity> -0.00061248 -0.00001490 -0.00003763 </velocity>
  </atom>
  <atom name="H122" species="hydrogen">
    <position> 0.71619164 19.17827995 13.37972243 </position>
    <velocity> 0.00056016 0.00003538 0.00004637 </velocity>
  </atom>
  <atom name="H123" species="hydrogen">
    <position> 5.92882180 22.94717522 0.85349311 </position>
    <velocity> 0.00032017 0.00011695 -0.00036070 </velocity>
  </atom>
  <atom name="H124" species="hydrogen">
    <position> 6.44664639 25.93590299 0.81638373 </position>
    <velocity> -0.00022897 -0.00036847 -0.00084607 </velocity>
  </atom>
  <atom name="H125" species="hydrogen">
    <position> -0.67277558 -8.65287346 10.61833424 </position>
    <velocity> -0.00002785 0.00007162 -0.00006298 </velocity>
  </atom>
  <atom name="H126" species="hydrogen">
    <position> -0.50181146 -7.83011601 13.49318607 </position>
    <velocity> 0.00005905 0.00057102 -0.00015615 </velocity>
  </atom>
  <atom name="H127" species="hydrogen">
    <position> 15.03623839 -5.25030111 0.80062646 </position>
    <velocity> 0.00064171 0.00006057 -0.00031178 </velocity>
  </atom>
  <atom name="H128" species="hydrogen">
    <position> 17.36454642 -4.53641227 -0.73722954 </position>
    <velocity> -0.00067103 -0.00014899 -0.00046595 </velocity>
  </atom>
</atomset>
</fpmd:sample>
